arby/__init__.py
arby/eim.py
arby/greedy.py
arby/integrals.py
arby-0.1a1.dist-info/LICENSE
arby-0.1a1.dist-info/METADATA
arby-0.1a1.dist-info/WHEEL
arby-0.1a1.dist-info/top_level.txt
arby-0.1a1.dist-info/RECORD
