Metadata-Version: 2.1
Name: arby
Version: 0.1a1
Summary: UNKNOWN
Home-page: https://gitlab.com/aaronuv/arby
Author: Aarón Villanueva
Author-email: aaron.villanueva@unc.edu.ar
License: UNKNOWN
Platform: UNKNOWN
Requires-Dist: numpy (>=1.6)
Requires-Dist: scipy (>=0.16)
